kraken_wsclient_py
